vega/__init__.py
vega/cli/__init__.py
vega/cli/commands/add.py
vega/cli/commands/generate.py
vega/cli/commands/init.py
vega/cli/commands/listener.py
vega/cli/commands/migrate.py
vega/cli/commands/update.py
vega/cli/commands/web.py
vega/cli/main.py
vega/cli/scaffolds/__init__.py
vega/cli/scaffolds/fastapi.py
vega/cli/scaffolds/sqlalchemy.py
vega/cli/scaffolds/vega_web.py
vega/cli/templates/__init__.py
vega/cli/templates/application/cqrs_command.py.j2
vega/cli/templates/application/cqrs_handler.py.j2
vega/cli/templates/application/cqrs_query.py.j2
vega/cli/templates/application/cqrs_response.py.j2
vega/cli/templates/application/interactor.py.j2
vega/cli/templates/application/mediator.py.j2
vega/cli/templates/application/service_interface.py.j2
vega/cli/templates/cli/command.py.j2
vega/cli/templates/cli/command_simple.py.j2
vega/cli/templates/cli/commands_init.py.j2
vega/cli/templates/components.py
vega/cli/templates/domain/aggregate.py.j2
vega/cli/templates/domain/entity.py.j2
vega/cli/templates/domain/event.py.j2
vega/cli/templates/domain/event_handler.py.j2
vega/cli/templates/domain/interactor.py.j2
vega/cli/templates/domain/mediator.py.j2
vega/cli/templates/domain/repository_interface.py.j2
vega/cli/templates/domain/service_interface.py.j2
vega/cli/templates/domain/value_object.py.j2
vega/cli/templates/infrastructure/listener.py.j2
vega/cli/templates/infrastructure/model.py.j2
vega/cli/templates/infrastructure/repository_impl.py.j2
vega/cli/templates/infrastructure/service_impl.py.j2
vega/cli/templates/loader.py
vega/cli/templates/project/.env.example
vega/cli/templates/project/.gitignore
vega/cli/templates/project/ARCHITECTURE.md.j2
vega/cli/templates/project/README.md.j2
vega/cli/templates/project/config.py.j2
vega/cli/templates/project/context_init.py.j2
vega/cli/templates/project/events_init.py.j2
vega/cli/templates/project/main.py.j2
vega/cli/templates/project/main_fastapi.py.j2
vega/cli/templates/project/main_standard.py.j2
vega_framework-0.3.27.dist-info/METADATA
vega_framework-0.3.27.dist-info/WHEEL
vega_framework-0.3.27.dist-info/entry_points.txt
vega_framework-0.3.27.dist-info/licenses/LICENSE
vega_framework-0.3.27.dist-info/RECORD
