Metadata-Version: 2.4
Name: vega-framework
Version: 0.3.27
Summary: Enterprise-ready Python framework with Domain-Driven Design (DDD), CQRS, and Clean Architecture for building maintainable and scalable applications.
License: MIT
License-File: LICENSE
Keywords: clean-architecture,domain-driven-design,ddd,cqrs,bounded-contexts,dependency-injection,framework,python,async,vega
Author: Roberto Ferro
Requires-Python: >=3.10,<4.0
Classifier: Development Status :: 3 - Alpha
Classifier: Intended Audience :: Developers
Classifier: License :: OSI Approved :: MIT License
Classifier: Programming Language :: Python :: 3
Classifier: Programming Language :: Python :: 3.10
Classifier: Programming Language :: Python :: 3.11
Classifier: Programming Language :: Python :: 3.12
Classifier: Programming Language :: Python :: 3.13
Classifier: Programming Language :: Python :: 3.14
Classifier: Topic :: Software Development :: Libraries :: Application Frameworks
Classifier: Topic :: Software Development :: Libraries :: Python Modules
Provides-Extra: sqs
Requires-Dist: aioboto3 (>=13.0,<14.0) ; extra == "sqs"
Requires-Dist: click (>=8.0,<9.0)
Requires-Dist: jinja2 (>=3.1,<4.0)
Requires-Dist: pydantic (>=2.0,<3.0)
Requires-Dist: pydantic-settings (>=2.0,<3.0)
Requires-Dist: python-dotenv (>=1.0,<2.0)
Requires-Dist: starlette (>=0.37,<0.38)
Requires-Dist: toml (>=0.10,<0.11)
Requires-Dist: uvicorn (>=0.27,<0.28)
Project-URL: Documentation, https://vega-framework.readthedocs.io
Project-URL: Homepage, https://github.com/RobyFerro/vega-framework
Project-URL: Repository, https://github.com/RobyFerro/vega-framework
